{"date":"2018-11-13T09:51:29.4813730+08:00","level":"DEBUG","logger":"Website","message":"StartUp....!","hostname":"PhilWang-MacBook-Pro"}
{"date":"2018-11-13T11:26:43.7370530+08:00","level":"DEBUG","logger":"Website","message":"StartUp....!","hostname":"PhilWang-MacBook-Pro"}
{"date":"2018-11-13T11:36:15.5353280+08:00","level":"DEBUG","logger":"Website","message":"StartUp....!","hostname":"PhilWang-MacBook-Pro"}
{"date":"2018-11-13T11:45:12.6504750+08:00","level":"DEBUG","logger":"Website","message":"StartUp....!","hostname":"PhilWang-MacBook-Pro"}
{"date":"2018-11-13T11:50:26.4860020+08:00","level":"DEBUG","logger":"Website","message":"StartUp....!","hostname":"PhilWang-MacBook-Pro"}
{"date":"2018-11-13T11:53:51.6997260+08:00","level":"DEBUG","logger":"Website","message":"StartUp....!","hostname":"PhilWang-MacBook-Pro"}
{"date":"2018-11-13T11:56:14.0398450+08:00","level":"DEBUG","logger":"Website","message":"StartUp....!","hostname":"PhilWang-MacBook-Pro"}
{"date":"2018-11-13T12:01:36.1490790+08:00","level":"DEBUG","logger":"Website","message":"StartUp....!","hostname":"PhilWang-MacBook-Pro"}
{"date":"2018-11-13T12:04:09.2074470+08:00","level":"DEBUG","logger":"Website","message":"StartUp....!","hostname":"PhilWang-MacBook-Pro"}
{"date":"2018-11-13T12:05:39.1987450+08:00","level":"DEBUG","logger":"Website","message":"StartUp....!","hostname":"PhilWang-MacBook-Pro"}
{"date":"2018-11-13T12:15:44.3507400+08:00","level":"DEBUG","logger":"Website","message":"StartUp....!","hostname":"PhilWang-MacBook-Pro"}
{"date":"2018-11-13T12:15:56.1035210+08:00","level":"DEBUG","logger":"Website","message":"StartUp....!","hostname":"PhilWang-MacBook-Pro"}
{"date":"2018-11-13T12:16:00.8832220+08:00","level":"DEBUG","logger":"Website","message":"StartUp....!","hostname":"PhilWang-MacBook-Pro"}
{"date":"2018-11-13T12:18:48.3636830+08:00","level":"DEBUG","logger":"Website","message":"StartUp....!","hostname":"PhilWang-MacBook-Pro"}
{"date":"2018-11-13T12:22:44.3104920+08:00","level":"DEBUG","logger":"Website","message":"StartUp....!","hostname":"PhilWang-MacBook-Pro"}
{"date":"2018-11-13T12:24:08.8544150+08:00","level":"DEBUG","logger":"Website","message":"StartUp....!","hostname":"PhilWang-MacBook-Pro"}
{"date":"2018-11-13T12:30:52.0770460+08:00","level":"DEBUG","logger":"Website","message":"StartUp....!","hostname":"PhilWang-MacBook-Pro"}
{"date":"2018-11-13T12:33:09.1867790+08:00","level":"DEBUG","logger":"Website","message":"StartUp....!","hostname":"PhilWang-MacBook-Pro"}
{"date":"2018-11-13T12:36:30.4895860+08:00","level":"DEBUG","logger":"Website","message":"StartUp....!","hostname":"PhilWang-MacBook-Pro"}
{"date":"2018-11-13T13:45:45.9955440+08:00","level":"DEBUG","logger":"Website","message":"StartUp....!","hostname":"PhilWang-MacBook-Pro"}
{"date":"2018-11-13T14:01:23.6964590+08:00","level":"DEBUG","logger":"Website","message":"StartUp....!","hostname":"PhilWang-MacBook-Pro"}
{"date":"2018-11-13T14:05:47.3867240+08:00","level":"DEBUG","logger":"Website","message":"StartUp....!","hostname":"PhilWang-MacBook-Pro"}
{"date":"2018-11-13T14:12:22.2610710+08:00","level":"DEBUG","logger":"Website","message":"StartUp....!","hostname":"PhilWang-MacBook-Pro"}
{"date":"2018-11-13T14:15:49.0036210+08:00","level":"DEBUG","logger":"Website","message":"StartUp....!","hostname":"PhilWang-MacBook-Pro"}
{"date":"2018-11-13T14:18:26.9531430+08:00","level":"DEBUG","logger":"Website","message":"StartUp....!","hostname":"PhilWang-MacBook-Pro"}
{"date":"2018-11-13T16:31:54.5302300+08:00","level":"DEBUG","logger":"Website","message":"StartUp....!","hostname":"PhilWang-MacBook-Pro"}
{"date":"2018-11-13T16:39:06.2443200+08:00","level":"DEBUG","logger":"Website","message":"StartUp....!","hostname":"PhilWang-MacBook-Pro"}
{"date":"2018-11-13T16:42:51.2623740+08:00","level":"DEBUG","logger":"Website","message":"StartUp....!","hostname":"PhilWang-MacBook-Pro"}
{"date":"2018-11-13T16:46:54.4041660+08:00","level":"DEBUG","logger":"Website","message":"StartUp....!","hostname":"PhilWang-MacBook-Pro"}
{"date":"2018-11-13T17:05:32.6337500+08:00","level":"DEBUG","logger":"Website","message":"StartUp....!","hostname":"PhilWang-MacBook-Pro"}
{"date":"2018-11-13T17:24:26.2327530+08:00","level":"DEBUG","logger":"Website","message":"StartUp....!","hostname":"PhilWang-MacBook-Pro"}
{"date":"2018-11-13T17:52:20.6444990+08:00","level":"DEBUG","logger":"Website","message":"StartUp....!","hostname":"PhilWang-MacBook-Pro"}
{"date":"2018-11-13T18:03:11.0060650+08:00","level":"DEBUG","logger":"Website","message":"StartUp....!","hostname":"PhilWang-MacBook-Pro"}
{"date":"2018-11-13T18:08:44.8774510+08:00","level":"DEBUG","logger":"Website","message":"StartUp....!","hostname":"PhilWang-MacBook-Pro"}
{"date":"2018-11-13T18:12:35.8947720+08:00","level":"DEBUG","logger":"Website","message":"StartUp....!","hostname":"PhilWang-MacBook-Pro"}
{"date":"2018-11-13T18:34:57.4410590+08:00","level":"DEBUG","logger":"Website","message":"StartUp....!","hostname":"PhilWang-MacBook-Pro"}
{"date":"2018-11-13T18:38:52.4701180+08:00","level":"DEBUG","logger":"Website","message":"StartUp....!","hostname":"PhilWang-MacBook-Pro"}
{"date":"2018-11-13T18:39:33.6789000+08:00","level":"DEBUG","logger":"Website","message":"StartUp....!","hostname":"PhilWang-MacBook-Pro"}
