{"date":"2018-08-28T16:05:54.8763010+08:00","level":"DEBUG","logger":"Website","message":"StartUp....","hostname":"Lulus-MacBook"}
{"date":"2018-08-28T16:10:42.2763010+08:00","level":"DEBUG","logger":"Website","message":"StartUp....","hostname":"Lulus-MacBook"}
{"date":"2018-08-28T16:12:09.4995660+08:00","level":"DEBUG","logger":"Website","message":"StartUp....","hostname":"Lulus-MacBook"}
{"date":"2018-08-28T16:14:08.5061300+08:00","level":"DEBUG","logger":"Website","message":"StartUp....","hostname":"Lulus-MacBook"}
{"date":"2018-08-28T16:15:49.3274100+08:00","level":"DEBUG","logger":"Website","message":"StartUp....","hostname":"Lulus-MacBook"}
{"date":"2018-08-28T16:18:51.3117700+08:00","level":"DEBUG","logger":"Website","message":"StartUp....","hostname":"Lulus-MacBook"}
{"date":"2018-08-28T16:19:51.8772600+08:00","level":"DEBUG","logger":"Website","message":"StartUp....","hostname":"Lulus-MacBook"}
{"date":"2018-08-28T16:23:56.5251100+08:00","level":"DEBUG","logger":"Website","message":"StartUp....","hostname":"Lulus-MacBook"}
{"date":"2018-08-28T16:24:05.5402840+08:00","level":"INFO","logger":"Website","message":"[ORDER]kkOrderNo:17KK0818582220000,priceType:price1||jtrOrderNo:69019514||jtrErr:\u8BA2\u5355\u5DF2\u7ECF\u63D0\u4EA4!","hostname":"Lulus-MacBook"}
{"date":"2018-08-28T16:24:05.7330970+08:00","level":"INFO","logger":"Website","message":"[PAY]kkOrderNo:17KK0818582220000,priceType:price1,jtrTktNo:690195149124,jtrErr:\u652F\u4ED8\u6210\u529F","hostname":"Lulus-MacBook"}
{"date":"2018-08-28T16:24:12.9455050+08:00","level":"INFO","logger":"Website","message":"[ORDER]kkOrderNo:17KK0818582220000,priceType:price2||jtrOrderNo:||jtrErr:\u4EA7\u54C1\u5DF2\u7ECF\u65E0\u6CD5\u83B7\u53D6\u5F53\u524D\u65E5\u671F\u7684\u4EF7\u683C","hostname":"Lulus-MacBook"}
{"date":"2018-08-28T16:24:13.7643250+08:00","level":"INFO","logger":"Website","message":"[PAY]kkOrderNo:17KK0818582220000,priceType:price2,jtrTktNo:,jtrErr:\u652F\u4ED8\u5931\u8D25\uFF0C\u539F\u56E0\uFF1A\u8BF7=\u6CA1\u6709\u8F93\u5165\u8BA2\u5355\u53F7","hostname":"Lulus-MacBook"}
{"date":"2018-08-28T16:24:59.3804550+08:00","level":"INFO","logger":"Website","message":"[ORDER]kkOrderNo:17KK0818582220001,priceType:price1||jtrOrderNo:69023009||jtrErr:\u5F55\u5165\u8BA2\u5355\u6210\u529F\uFF01\u672C\u8BA2\u5355\u9700\u8981\u5728\u7EBF\u652F\u4ED8\u540E\u624D\u80FD\u6709\u6548\uFF01","hostname":"Lulus-MacBook"}
{"date":"2018-08-28T16:25:08.4881360+08:00","level":"INFO","logger":"Website","message":"[PAY]kkOrderNo:17KK0818582220001,priceType:price1,jtrTktNo:690230093096,jtrErr:\u652F\u4ED8\u6210\u529F","hostname":"Lulus-MacBook"}
{"date":"2018-08-28T16:25:10.6553540+08:00","level":"INFO","logger":"Website","message":"[ORDER]kkOrderNo:17KK0818582220001,priceType:price2||jtrOrderNo:||jtrErr:\u4EA7\u54C1\u5DF2\u7ECF\u65E0\u6CD5\u83B7\u53D6\u5F53\u524D\u65E5\u671F\u7684\u4EF7\u683C","hostname":"Lulus-MacBook"}
{"date":"2018-08-28T16:25:10.7046920+08:00","level":"INFO","logger":"Website","message":"[PAY]kkOrderNo:17KK0818582220001,priceType:price2,jtrTktNo:,jtrErr:\u652F\u4ED8\u5931\u8D25\uFF0C\u539F\u56E0\uFF1A\u8BF7=\u6CA1\u6709\u8F93\u5165\u8BA2\u5355\u53F7","hostname":"Lulus-MacBook"}
{"date":"2018-08-28T17:28:12.2202360+08:00","level":"DEBUG","logger":"Website","message":"StartUp....","hostname":"Lulus-MacBook"}
{"date":"2018-08-28T17:28:28.8401480+08:00","level":"INFO","logger":"Website","message":"[ORDER]kkOrderNo:17KK0818582220001,priceType:price1,jtrOrderNo:69023009,jtrErr:\u8BA2\u5355\u5DF2\u7ECF\u63D0\u4EA4!","hostname":"Lulus-MacBook"}
{"date":"2018-08-28T17:28:56.1160300+08:00","level":"INFO","logger":"Website","message":"[PAY]kkOrderNo:17KK0818582220001,priceType:price1,jtrTktNo:,jtrErr:\u652F\u4ED8\u6210\u529F","hostname":"Lulus-MacBook"}
{"date":"2018-08-28T17:29:15.3420980+08:00","level":"INFO","logger":"Website","message":"[ORDER]kkOrderNo:17KK0818582220001,priceType:price2,jtrOrderNo:,jtrErr:\u4EA7\u54C1\u5DF2\u7ECF\u65E0\u6CD5\u83B7\u53D6\u5F53\u524D\u65E5\u671F\u7684\u4EF7\u683C","hostname":"Lulus-MacBook"}
{"date":"2018-08-28T17:29:15.3800280+08:00","level":"INFO","logger":"Website","message":"[PAY]kkOrderNo:17KK0818582220001,priceType:price2,jtrTktNo:,jtrErr:\u652F\u4ED8\u5931\u8D25\uFF0C\u539F\u56E0\uFF1A\u8BF7=\u6CA1\u6709\u8F93\u5165\u8BA2\u5355\u53F7","hostname":"Lulus-MacBook"}
